phrappy/__init__.py
phrappy/_meta.py
phrappy/async_client.py
phrappy/client.py
phrappy/exceptions.py
phrappy/py.typed
phrappy/async_tags/__init__.py
phrappy/async_tags/additional_workflow_step.py
phrappy/async_tags/analysis.py
phrappy/async_tags/async_request.py
phrappy/async_tags/authentication.py
phrappy/async_tags/bilingual_file.py
phrappy/async_tags/business_unit.py
phrappy/async_tags/buyer.py
phrappy/async_tags/client.py
phrappy/async_tags/connector.py
phrappy/async_tags/conversations.py
phrappy/async_tags/cost_center.py
phrappy/async_tags/custom_fields.py
phrappy/async_tags/custom_file_type.py
phrappy/async_tags/domain.py
phrappy/async_tags/due_date_scheme.py
phrappy/async_tags/email_template.py
phrappy/async_tags/file.py
phrappy/async_tags/glossary.py
phrappy/async_tags/importsettings.py
phrappy/async_tags/job.py
phrappy/async_tags/language_ai.py
phrappy/async_tags/language_quality_assessment.py
phrappy/async_tags/machine_translation.py
phrappy/async_tags/machine_translation_settings.py
phrappy/async_tags/mapping.py
phrappy/async_tags/net_rate_scheme.py
phrappy/async_tags/notifications.py
phrappy/async_tags/price_list.py
phrappy/async_tags/project.py
phrappy/async_tags/project_reference_file.py
phrappy/async_tags/project_template.py
phrappy/async_tags/provider.py
phrappy/async_tags/quality_assurance.py
phrappy/async_tags/quote.py
phrappy/async_tags/scim.py
phrappy/async_tags/segment.py
phrappy/async_tags/segmentation_rules.py
phrappy/async_tags/service.py
phrappy/async_tags/spell_check.py
phrappy/async_tags/sub_domain.py
phrappy/async_tags/supported_languages.py
phrappy/async_tags/term_base.py
phrappy/async_tags/translation.py
phrappy/async_tags/translation_memory.py
phrappy/async_tags/user.py
phrappy/async_tags/vendor.py
phrappy/async_tags/webhook.py
phrappy/async_tags/workflow_step.py
phrappy/async_tags/workflowchanges.py
phrappy/async_tags/xml_assistant.py
phrappy/exceptions/__init__.py
phrappy/models/__init__.py
phrappy/models/header_json_models.py
phrappy-0.2.0.dist-info/METADATA
phrappy-0.2.0.dist-info/WHEEL
phrappy-0.2.0.dist-info/licenses/LICENSE
phrappy-0.2.0.dist-info/RECORD
