Metadata-Version: 2.4
Name: phrappy
Version: 0.2.0
Summary: Unofficial typed Python Client for the Phrase TMS (Memsource) API.
Project-URL: Homepage, https://github.com/kuhnemann/phrappy
Author-email: Henrik Kühnemann <hk@yellownape.se>
License: Copyright © 2025 Henrik Kühnemann
License-File: LICENSE
Keywords: api,localization,phrase,tms,translation
Classifier: License :: OSI Approved :: MIT License
Classifier: Programming Language :: Python
Classifier: Programming Language :: Python :: 3
Classifier: Typing :: Typed
Requires-Python: >=3.10
Requires-Dist: httpx>=0.28.1
Requires-Dist: pydantic<3.0.0,>=2.0.0
Provides-Extra: dev
Requires-Dist: pytest-asyncio>=0.23; extra == 'dev'
Requires-Dist: pytest-httpx>=0.30; extra == 'dev'
Requires-Dist: pytest-recording>=0.13.1; extra == 'dev'
Requires-Dist: pytest>=8; extra == 'dev'
Requires-Dist: python-dotenv>=1.1.0; extra == 'dev'
Requires-Dist: ruff>=0.12.11; extra == 'dev'
